tools/__init__.py
tools/general.py
tools/panda.py
tools/prophet.py
tools_d1zcord-0.0.1.dist-info/LICENSE
tools_d1zcord-0.0.1.dist-info/METADATA
tools_d1zcord-0.0.1.dist-info/WHEEL
tools_d1zcord-0.0.1.dist-info/top_level.txt
tools_d1zcord-0.0.1.dist-info/RECORD
